{
  "folder": "JDBC",
  "total_services": 1,
  "services": [
    {
      "name": "pub.jdbc:getPoolInfo",
      "folder": "JDBC",
      "description": "Last Updated: 2026-02-17",
      "inputs": [
        {
          "name": "functionalAlias",
          "type": "String",
          "description": "Name of the Integration Server functional alias for which you want to obtain JDBC information.",
          "optional": false
        },
        {
          "name": "getConnectionWait",
          "type": "String",
          "description": "Optional. Number of milliseconds the service will wait to obtain a connection to a JDBC connection pool. The default is 10 seconds (10000 milliseconds). If a connection is not obtained within this time, the service ends with a status of fail.",
          "optional": true
        }
      ],
      "outputs": [
        {
          "name": "minConnections",
          "type": "String",
          "description": "The minimum number of connections the pool can have.",
          "optional": false
        },
        {
          "name": "maxConnections",
          "type": "String",
          "description": "The maximum number of connections the pool can have.",
          "optional": false
        },
        {
          "name": "totalConnections",
          "type": "String",
          "description": "The total number of connections currently in the pool. This number includes connections that are already in use and connections that are available for use.",
          "optional": false
        },
        {
          "name": "availableConnections",
          "type": "String",
          "description": "The number of connections that are available for use.",
          "optional": false
        },
        {
          "name": "status",
          "type": "String",
          "description": "A status indicating whether the service was able to connect to the pool. A value of: Active indicates that the service was able to connect to the JDBC pool. Inactive indicates that the service was not able to connect to the JDBC pool or an invalid functional alias was specified. If the attempt to connect to the JDBC pool failed with a SQLException, the service might throw an exception. If the service does not throw an exception, it will return a message in the message variable.",
          "optional": false
        }
      ],
      "source_url": "SSL8N8_11.1/is_bis_reference/A73644.html"
    }
  ]
}